sphinx_ref_in_plantuml_hyperlinks/__init__.py
sphinx_ref_in_plantuml_hyperlinks-0.7.3.dist-info/LICENSE
sphinx_ref_in_plantuml_hyperlinks-0.7.3.dist-info/METADATA
sphinx_ref_in_plantuml_hyperlinks-0.7.3.dist-info/WHEEL
sphinx_ref_in_plantuml_hyperlinks-0.7.3.dist-info/RECORD
